{"v":"4.8.0","meta":{"g":"LottieFiles AE 3.4.5","a":"","k":"","d":"","tc":""},"fr":30,"ip":0,"op":180,"w":1934,"h":1562,"nm":"Legs up the Wall Pose","ddd":0,"assets":[],"layers":[{"ddd":0,"ind":1,"ty":4,"nm":"Layer 6 Outlines","sr":1,"ks":{"o":{"a":0,"k":100,"ix":11},"r":{"a":0,"k":0,"ix":10},"p":{"a":0,"k":[967.002,780.606,0],"ix":2},"a":{"a":0,"k":[689.914,364.756,0],"ix":1},"s":{"a":0,"k":[100,100,100],"ix":6}},"ao":0,"shapes":[{"ty":"gr","it":[{"ind":0,"ty":"sh","ix":1,"ks":{"a":0,"k":{"i":[[3.978,2.454],[12.924,-0.585],[-4.496,-2.478],[-1.478,0.854]],"o":[[-3.666,-0.932],[-1.591,4.085],[19.871,-1.296],[13.962,-9.936]],"v":[[16.064,-10.6],[-24.698,-14.631],[-23.254,15.217],[13.788,11.639]],"c":true},"ix":2},"nm":"Path 1","mn":"ADBE Vector Shape - Group","hd":false},{"ty":"fl","c":{"a":0,"k":[0.936999990426,0.611999990426,0.46699999641,1],"ix":4},"o":{"a":0,"k":100,"ix":5},"r":1,"bm":0,"nm":"Fill 1","mn":"ADBE Vector Graphic - Fill","hd":false},{"ty":"tr","p":{"a":0,"k":[611.982,677.356],"ix":2},"a":{"a":0,"k":[0,0],"ix":1},"s":{"a":0,"k":[100,100],"ix":3},"r":{"a":0,"k":0,"ix":6},"o":{"a":0,"k":100,"ix":7},"sk":{"a":0,"k":0,"ix":4},"sa":{"a":0,"k":0,"ix":5},"nm":"Transform"}],"nm":"Group 5","np":2,"cix":2,"bm":0,"ix":1,"mn":"ADBE Vector Group","hd":false},{"ty":"gr","it":[{"ind":0,"ty":"sh","ix":1,"ks":{"a":0,"k":{"i":[[0,0],[3.272,-0.909],[3.527,-2.026],[1.502,-2.29],[-4.259,4.072],[0,0],[-3.547,0.152],[-5.32,-0.372]],"o":[[-5.112,-0.262],[-4.348,1.194],[-1.544,0.876],[-4.301,6.511],[1.275,-1.197],[4.24,-1.268],[2.519,-0.097],[3.314,-1.915]],"v":[[20.654,-11.628],[0.383,-9.666],[-12.591,-3.638],[-17.221,3.304],[-10.575,7.818],[-5.018,2.15],[8.154,-1.247],[18.209,-1.828]],"c":true},"ix":2},"nm":"Path 1","mn":"ADBE Vector Shape - Group","hd":false},{"ty":"fl","c":{"a":0,"k":[0.936999990426,0.611999990426,0.46699999641,1],"ix":4},"o":{"a":0,"k":100,"ix":5},"r":1,"bm":0,"nm":"Fill 1","mn":"ADBE Vector Graphic - Fill","hd":false},{"ty":"tr","p":{"a":0,"k":[570.52,694.401],"ix":2},"a":{"a":0,"k":[0,0],"ix":1},"s":{"a":0,"k":[100,100],"ix":3},"r":{"a":0,"k":0,"ix":6},"o":{"a":0,"k":100,"ix":7},"sk":{"a":0,"k":0,"ix":4},"sa":{"a":0,"k":0,"ix":5},"nm":"Transform"}],"nm":"Group 6","np":2,"cix":2,"bm":0,"ix":2,"mn":"ADBE Vector Group","hd":false},{"ty":"gr","it":[{"ind":0,"ty":"sh","ix":1,"ks":{"a":0,"k":{"i":[[-9.09,1.132],[1.031,-0.678],[2.183,-0.24],[3.606,-1.3]],"o":[[0.075,1.626],[-4.676,-0.023],[-3.059,0.316],[7.603,-6.594]],"v":[[13.448,-3.517],[12.231,0.319],[-2.134,0.815],[-13.523,3.517]],"c":true},"ix":2},"nm":"Path 1","mn":"ADBE Vector Shape - Group","hd":false},{"ty":"fl","c":{"a":0,"k":[0.898000021542,0.545000023935,0.404000016755,1],"ix":4},"o":{"a":0,"k":100,"ix":5},"r":1,"bm":0,"nm":"Fill 1","mn":"ADBE Vector Graphic - Fill","hd":false},{"ty":"tr","p":{"a":0,"k":[578.611,685.383],"ix":2},"a":{"a":0,"k":[0,0],"ix":1},"s":{"a":0,"k":[100,100],"ix":3},"r":{"a":0,"k":0,"ix":6},"o":{"a":0,"k":100,"ix":7},"sk":{"a":0,"k":0,"ix":4},"sa":{"a":0,"k":0,"ix":5},"nm":"Transform"}],"nm":"Group 7","np":2,"cix":2,"bm":0,"ix":3,"mn":"ADBE Vector Group","hd":false},{"ty":"gr","it":[{"ind":0,"ty":"sh","ix":1,"ks":{"a":0,"k":{"i":[[-10.902,1.366],[1.25,-0.816],[2.62,-0.278],[4.332,-1.55]],"o":[[0.086,1.97],[-5.579,-0.027],[-3.66,0.392],[9.125,-7.893]],"v":[[16.121,-4.218],[14.639,0.388],[-2.564,0.987],[-16.207,4.218]],"c":true},"ix":2},"nm":"Path 1","mn":"ADBE Vector Shape - Group","hd":false},{"ty":"fl","c":{"a":0,"k":[0.898000021542,0.545000023935,0.404000016755,1],"ix":4},"o":{"a":0,"k":100,"ix":5},"r":1,"bm":0,"nm":"Fill 1","mn":"ADBE Vector Graphic - Fill","hd":false},{"ty":"tr","p":{"a":0,"k":[576.053,685.093],"ix":2},"a":{"a":0,"k":[0,0],"ix":1},"s":{"a":0,"k":[100,100],"ix":3},"r":{"a":0,"k":0,"ix":6},"o":{"a":0,"k":100,"ix":7},"sk":{"a":0,"k":0,"ix":4},"sa":{"a":0,"k":0,"ix":5},"nm":"Transform"}],"nm":"Group 8","np":2,"cix":2,"bm":0,"ix":4,"mn":"ADBE Vector Group","hd":false},{"ty":"gr","it":[{"ind":0,"ty":"sh","ix":1,"ks":{"a":0,"k":{"i":[[0,0],[3.46,-0.86],[3.934,-1.669],[2.063,-2.105],[-5.101,3.492],[-4.531,1.632],[-3.689,0.398],[-5.579,-0.027]],"o":[[-5.363,0.073],[-6.559,1.616],[-4.219,1.791],[-4.392,4.494],[1.543,-1.062],[4.348,-1.586],[2.619,-0.279],[3.357,-2.201]],"v":[[22.471,-12.674],[3.901,-9.797],[-10.884,-5.725],[-21.444,4.998],[-15.656,9.182],[-8.52,2.868],[5.277,-0.429],[22.479,-1.028]],"c":true},"ix":2},"nm":"Path 1","mn":"ADBE Vector Shape - Group","hd":false},{"ty":"fl","c":{"a":0,"k":[0.936999990426,0.611999990426,0.46699999641,1],"ix":4},"o":{"a":0,"k":100,"ix":5},"r":1,"bm":0,"nm":"Fill 1","mn":"ADBE Vector Graphic - Fill","hd":false},{"ty":"tr","p":{"a":0,"k":[568.213,686.509],"ix":2},"a":{"a":0,"k":[0,0],"ix":1},"s":{"a":0,"k":[100,100],"ix":3},"r":{"a":0,"k":0,"ix":6},"o":{"a":0,"k":100,"ix":7},"sk":{"a":0,"k":0,"ix":4},"sa":{"a":0,"k":0,"ix":5},"nm":"Transform"}],"nm":"Group 9","np":2,"cix":2,"bm":0,"ix":5,"mn":"ADBE Vector Group","hd":false},{"ty":"gr","it":[{"ind":0,"ty":"sh","ix":1,"ks":{"a":0,"k":{"i":[[-19.597,-0.03],[1.667,-1.069],[2.659,-0.264],[4.411,-1.574],[0.97,-1.533],[1.56,0.128]],"o":[[0.378,2.602],[-5.649,-0.057],[-3.748,0.377],[-4.592,1.651],[-1.127,1.779],[7.23,-16.46]],"v":[[22.871,-10.838],[21.53,-4.346],[4.097,-3.842],[-9.911,-0.597],[-18.826,8.419],[-23.249,10.74]],"c":true},"ix":2},"nm":"Path 1","mn":"ADBE Vector Shape - Group","hd":false},{"ty":"fl","c":{"a":0,"k":[0.898000021542,0.545000023935,0.404000016755,1],"ix":4},"o":{"a":0,"k":100,"ix":5},"r":1,"bm":0,"nm":"Fill 1","mn":"ADBE Vector Graphic - Fill","hd":false},{"ty":"tr","p":{"a":0,"k":[566.368,683.819],"ix":2},"a":{"a":0,"k":[0,0],"ix":1},"s":{"a":0,"k":[100,100],"ix":3},"r":{"a":0,"k":0,"ix":6},"o":{"a":0,"k":100,"ix":7},"sk":{"a":0,"k":0,"ix":4},"sa":{"a":0,"k":0,"ix":5},"nm":"Transform"}],"nm":"Group 10","np":2,"cix":2,"bm":0,"ix":6,"mn":"ADBE Vector Group","hd":false},{"ty":"gr","it":[{"ind":0,"ty":"sh","ix":1,"ks":{"a":0,"k":{"i":[[0,0],[3.515,-0.843],[3.996,-1.679],[2.309,-3.269],[-2.978,4.709],[-4.592,1.651],[-3.749,0.377],[-5.649,-0.057]],"o":[[-5.442,0.049],[-6.666,1.608],[-4.294,1.815],[-3.69,5.227],[0.97,-1.533],[4.411,-1.574],[2.659,-0.264],[3.41,-2.206]],"v":[[23.707,-14.637],[4.159,-13.051],[-13.228,-7.52],[-23.365,6.375],[-16.711,9.927],[-7.796,0.911],[6.214,-2.335],[23.646,-2.839]],"c":true},"ix":2},"nm":"Path 1","mn":"ADBE Vector Shape - Group","hd":false},{"ty":"fl","c":{"a":0,"k":[0.936999990426,0.611999990426,0.46699999641,1],"ix":4},"o":{"a":0,"k":100,"ix":5},"r":1,"bm":0,"nm":"Fill 1","mn":"ADBE Vector Graphic - Fill","hd":false},{"ty":"tr","p":{"a":0,"k":[564.253,682.311],"ix":2},"a":{"a":0,"k":[0,0],"ix":1},"s":{"a":0,"k":[100,100],"ix":3},"r":{"a":0,"k":0,"ix":6},"o":{"a":0,"k":100,"ix":7},"sk":{"a":0,"k":0,"ix":4},"sa":{"a":0,"k":0,"ix":5},"nm":"Transform"}],"nm":"Group 11","np":2,"cix":2,"bm":0,"ix":7,"mn":"ADBE Vector Group","hd":false},{"ty":"gr","it":[{"ind":0,"ty":"sh","ix":1,"ks":{"a":0,"k":{"i":[[-17.192,2.032],[2.627,-1.227],[2.665,0.075],[4.614,-1.005],[1.8,-0.656],[-3.767,5.401],[-0.55,1.037]],"o":[[0.368,3.481],[-5.564,-0.796],[-3.772,-0.115],[-4.831,1.019],[-6.649,2.464],[0.558,-0.795],[14.04,-10.644]],"v":[[26.243,-10.385],[24.203,0.236],[3.846,-2.794],[-7.421,-0.089],[-16.039,7.921],[-23.063,4.393],[-21.466,1.592]],"c":true},"ix":2},"nm":"Path 1","mn":"ADBE Vector Shape - Group","hd":false},{"ty":"fl","c":{"a":0,"k":[0.898000021542,0.545000023935,0.404000016755,1],"ix":4},"o":{"a":0,"k":100,"ix":5},"r":1,"bm":0,"nm":"Fill 1","mn":"ADBE Vector Graphic - Fill","hd":false},{"ty":"tr","p":{"a":0,"k":[567.056,675.751],"ix":2},"a":{"a":0,"k":[0,0],"ix":1},"s":{"a":0,"k":[100,100],"ix":3},"r":{"a":0,"k":0,"ix":6},"o":{"a":0,"k":100,"ix":7},"sk":{"a":0,"k":0,"ix":4},"sa":{"a":0,"k":0,"ix":5},"nm":"Transform"}],"nm":"Group 12","np":2,"cix":2,"bm":0,"ix":8,"mn":"ADBE Vector Group","hd":false},{"ty":"gr","it":[{"ind":0,"ty":"sh","ix":1,"ks":{"a":0,"k":{"i":[[0,0],[3.618,-0.379],[3.497,-2.487],[1.698,-2.417],[-6.649,2.463],[-4.831,1.019],[-3.773,-0.115],[-5.565,-0.796]],"o":[[-5.374,-0.659],[-6.825,0.726],[-3.494,2.464],[-3.767,5.401],[1.799,-0.656],[4.615,-1.005],[2.664,0.075],[3.753,-1.759]],"v":[[25.341,-11.327],[-1.626,-9.757],[-17.325,-2.904],[-23.626,5.995],[-16.602,9.522],[-7.985,1.512],[3.283,-1.193],[23.64,1.837]],"c":true},"ix":2},"nm":"Path 1","mn":"ADBE Vector Shape - Group","hd":false},{"ty":"fl","c":{"a":0,"k":[0.936999990426,0.611999990426,0.46699999641,1],"ix":4},"o":{"a":0,"k":100,"ix":5},"r":1,"bm":0,"nm":"Fill 1","mn":"ADBE Vector Graphic - Fill","hd":false},{"ty":"tr","p":{"a":0,"k":[567.619,674.149],"ix":2},"a":{"a":0,"k":[0,0],"ix":1},"s":{"a":0,"k":[100,100],"ix":3},"r":{"a":0,"k":0,"ix":6},"o":{"a":0,"k":100,"ix":7},"sk":{"a":0,"k":0,"ix":4},"sa":{"a":0,"k":0,"ix":5},"nm":"Transform"}],"nm":"Group 13","np":2,"cix":2,"bm":0,"ix":9,"mn":"ADBE Vector Group","hd":false},{"ty":"gr","it":[{"ind":0,"ty":"sh","ix":1,"ks":{"a":0,"k":{"i":[[-2.508,0.396],[11.176,1.426],[2.699,0.138],[-9.457,-2.286]],"o":[[4.618,-0.745],[-11.185,-1.415],[-2.703,-0.134],[9.472,2.281]],"v":[[27.313,5.022],[4.206,-3.24],[-25.733,-5.465],[-22.474,3.318]],"c":true},"ix":2},"nm":"Path 1","mn":"ADBE Vector Shape - Group","hd":false},{"ty":"fl","c":{"a":0,"k":[0.936999990426,0.611999990426,0.46699999641,1],"ix":4},"o":{"a":0,"k":100,"ix":5},"r":1,"bm":0,"nm":"Fill 1","mn":"ADBE Vector Graphic - Fill","hd":false},{"ty":"tr","p":{"a":0,"k":[594,663.228],"ix":2},"a":{"a":0,"k":[0,0],"ix":1},"s":{"a":0,"k":[100,100],"ix":3},"r":{"a":0,"k":0,"ix":6},"o":{"a":0,"k":100,"ix":7},"sk":{"a":0,"k":0,"ix":4},"sa":{"a":0,"k":0,"ix":5},"nm":"Transform"}],"nm":"Group 14","np":2,"cix":2,"bm":0,"ix":10,"mn":"ADBE Vector Group","hd":false},{"ty":"gr","it":[{"ind":0,"ty":"sh","ix":1,"ks":{"a":0,"k":{"i":[[17.533,-6.203],[18.666,0.447],[18.065,-4.287],[-22.861,6.572],[-104.783,-12.913]],"o":[[-23.085,8.168],[-44.561,-1.066],[-18.065,4.286],[22.861,-6.571],[39.495,6.841]],"v":[[126.296,25.484],[62.063,32.994],[-120.131,31.635],[-129.172,8.814],[112.538,-23.008]],"c":true},"ix":2},"nm":"Path 1","mn":"ADBE Vector Shape - Group","hd":false},{"ty":"fl","c":{"a":0,"k":[0.936999990426,0.611999990426,0.46699999641,1],"ix":4},"o":{"a":0,"k":100,"ix":5},"r":1,"bm":0,"nm":"Fill 1","mn":"ADBE Vector Graphic - Fill","hd":false},{"ty":"tr","p":{"a":0,"k":[736.947,659.112],"ix":2},"a":{"a":0,"k":[0,0],"ix":1},"s":{"a":0,"k":[100,100],"ix":3},"r":{"a":0,"k":0,"ix":6},"o":{"a":0,"k":100,"ix":7},"sk":{"a":0,"k":0,"ix":4},"sa":{"a":0,"k":0,"ix":5},"nm":"Transform"}],"nm":"Group 15","np":2,"cix":2,"bm":0,"ix":11,"mn":"ADBE Vector Group","hd":false},{"ty":"gr","it":[{"ind":0,"ty":"sh","ix":1,"ks":{"a":0,"k":{"i":[[-16.076,11.491],[-50.925,6.372],[-20.461,0.509],[-0.915,-50.095],[37.826,9.355],[33.457,1.293]],"o":[[0,0],[50.924,-6.371],[20.462,-0.509],[0.914,50.094],[-37.827,-9.356],[-33.456,-1.293]],"v":[[-115.628,-6.159],[-44.313,-34.456],[59.094,-52.143],[130.791,-2.57],[28.203,43.31],[-95.156,33.247]],"c":true},"ix":2},"nm":"Path 1","mn":"ADBE Vector Shape - Group","hd":false},{"ty":"fl","c":{"a":0,"k":[0.936999990426,0.611999990426,0.46699999641,1],"ix":4},"o":{"a":0,"k":100,"ix":5},"r":1,"bm":0,"nm":"Fill 1","mn":"ADBE Vector Graphic - Fill","hd":false},{"ty":"tr","p":{"a":0,"k":[946.357,650.965],"ix":2},"a":{"a":0,"k":[0,0],"ix":1},"s":{"a":0,"k":[100,100],"ix":3},"r":{"a":0,"k":0,"ix":6},"o":{"a":0,"k":100,"ix":7},"sk":{"a":0,"k":0,"ix":4},"sa":{"a":0,"k":0,"ix":5},"nm":"Transform"}],"nm":"Group 16","np":2,"cix":2,"bm":0,"ix":12,"mn":"ADBE Vector Group","hd":false},{"ty":"gr","it":[{"ind":0,"ty":"sh","ix":1,"ks":{"a":0,"k":{"i":[[-50.535,0.715],[-11.714,63.78],[124.851,-12.356],[-105.423,-51.181]],"o":[[0,0],[0,0],[0,0],[110.499,53.646]],"v":[[160.296,32.832],[156.316,-90.306],[-32.549,-84.995],[-54.873,43.705]],"c":true},"ix":2},"nm":"Path 1","mn":"ADBE Vector Shape - Group","hd":false},{"ty":"fl","c":{"a":0,"k":[0.195999998205,0.195999998205,0.298000021542,1],"ix":4},"o":{"a":0,"k":100,"ix":5},"r":1,"bm":0,"nm":"Fill 1","mn":"ADBE Vector Graphic - Fill","hd":false},{"ty":"tr","p":{"a":0,"k":[614.238,627.482],"ix":2},"a":{"a":0,"k":[0,0],"ix":1},"s":{"a":0,"k":[100,100],"ix":3},"r":{"a":0,"k":0,"ix":6},"o":{"a":0,"k":100,"ix":7},"sk":{"a":0,"k":0,"ix":4},"sa":{"a":0,"k":0,"ix":5},"nm":"Transform"}],"nm":"Group 17","np":2,"cix":2,"bm":0,"ix":13,"mn":"ADBE Vector Group","hd":false},{"ty":"gr","it":[{"ind":0,"ty":"sh","ix":1,"ks":{"a":0,"k":{"i":[[2.757,-25.147],[94.368,30.495],[-60.5,-3.791]],"o":[[0,0],[-89.376,-28.881],[54.747,3.43]],"v":[[87.243,5.712],[-2.496,41.494],[-13.39,-68.197]],"c":true},"ix":2},"nm":"Path 1","mn":"ADBE Vector Shape - Group","hd":false},{"ty":"fl","c":{"a":0,"k":[0.898000021542,0.545000023935,0.404000016755,1],"ix":4},"o":{"a":0,"k":100,"ix":5},"r":1,"bm":0,"nm":"Fill 1","mn":"ADBE Vector Graphic - Fill","hd":false},{"ty":"tr","p":{"a":0,"k":[1003.935,645.635],"ix":2},"a":{"a":0,"k":[0,0],"ix":1},"s":{"a":0,"k":[100,100],"ix":3},"r":{"a":0,"k":0,"ix":6},"o":{"a":0,"k":100,"ix":7},"sk":{"a":0,"k":0,"ix":4},"sa":{"a":0,"k":0,"ix":5},"nm":"Transform"}],"nm":"Group 18","np":2,"cix":2,"bm":0,"ix":14,"mn":"ADBE Vector Group","hd":false},{"ty":"gr","it":[{"ind":0,"ty":"sh","ix":1,"ks":{"a":0,"k":{"i":[[108.051,32.709],[45.184,6.293],[-7.786,51.521],[-1.298,-0.202],[-35.079,-3.503],[-17.708,-20.371],[2.186,-7.604],[-23.217,-24.68]],"o":[[-26.771,-8.111],[-5.474,-20.234],[14.608,0.814],[10.978,-10.094],[27.428,2.747],[1.901,6.381],[0,0],[18.225,33.954]],"v":[[12.695,73.032],[-103.354,50.561],[-112.959,-73.883],[-86.614,-72.186],[-27.859,-102.238],[32.967,-62.558],[33.453,-41.115],[99.01,4.178]],"c":true},"ix":2},"nm":"Path 1","mn":"ADBE Vector Shape - Group","hd":false},{"ty":"fl","c":{"a":0,"k":[0.984000052658,0.773000021542,0.365000017952,1],"ix":4},"o":{"a":0,"k":100,"ix":5},"r":1,"bm":0,"nm":"Fill 1","mn":"ADBE Vector Graphic - Fill","hd":false},{"ty":"tr","p":{"a":0,"k":[985.605,616.534],"ix":2},"a":{"a":0,"k":[0,0],"ix":1},"s":{"a":0,"k":[100,100],"ix":3},"r":{"a":0,"k":0,"ix":6},"o":{"a":0,"k":100,"ix":7},"sk":{"a":0,"k":0,"ix":4},"sa":{"a":0,"k":0,"ix":5},"nm":"Transform"}],"nm":"Group 19","np":2,"cix":2,"bm":0,"ix":15,"mn":"ADBE Vector Group","hd":false},{"ty":"gr","it":[{"ty":"gr","it":[{"ind":0,"ty":"sh","ix":1,"ks":{"a":0,"k":{"i":[[6.345,6.323],[-17.602,-2.48],[-24.24,-38.371],[40.006,-26.146],[33.767,10.225],[-17.955,10.952],[-0.919,12.747],[10.29,-3.795],[0,0],[-14.503,10.005]],"o":[[0,0],[17.602,2.48],[24.24,38.372],[-40.008,26.145],[-3.943,-9.305],[17.956,-10.951],[0.921,-12.749],[-10.291,3.793],[5.688,-5.731],[14.504,-10.003]],"v":[[-25.725,-82.903],[-7.348,-90.839],[60.668,-44.188],[37.795,67.174],[-80.965,79.024],[-51.499,30.148],[-18.037,2.198],[-40.786,-15.159],[-56.35,-17.687],[-35.35,-34.898]],"c":true},"ix":2},"nm":"Path 1","mn":"ADBE Vector Shape - Group","hd":false},{"ty":"fl","c":{"a":0,"k":[0.419999994016,0.231000010173,0.195999998205,1],"ix":4},"o":{"a":0,"k":100,"ix":5},"r":1,"bm":0,"nm":"Fill 1","mn":"ADBE Vector Graphic - Fill","hd":false},{"ty":"tr","p":{"a":0,"k":[1212.099,589.782],"ix":2},"a":{"a":0,"k":[0,0],"ix":1},"s":{"a":0,"k":[100,100],"ix":3},"r":{"a":0,"k":0,"ix":6},"o":{"a":0,"k":100,"ix":7},"sk":{"a":0,"k":0,"ix":4},"sa":{"a":0,"k":0,"ix":5},"nm":"Transform"}],"nm":"Group 1","np":2,"cix":2,"bm":0,"ix":1,"mn":"ADBE Vector Group","hd":false},{"ty":"gr","it":[{"ind":0,"ty":"sh","ix":1,"ks":{"a":0,"k":{"i":[[0,0],[-4.062,-9.869],[11.212,-15.445],[15.301,9.96]],"o":[[0,0],[4.061,9.872],[-11.213,15.446],[-15.301,-9.96]],"v":[[8.408,-34.008],[26.179,-28.909],[16.491,20.298],[-14.939,28.818]],"c":true},"ix":2},"nm":"Path 1","mn":"ADBE Vector Shape - Group","hd":false},{"ty":"fl","c":{"a":0,"k":[0.995999983245,0.783999992819,0.356999984442,1],"ix":4},"o":{"a":0,"k":100,"ix":5},"r":1,"bm":0,"nm":"Fill 1","mn":"ADBE Vector Graphic - Fill","hd":false},{"ty":"tr","p":{"a":0,"k":[1270.248,616.785],"ix":2},"a":{"a":0,"k":[0,0],"ix":1},"s":{"a":0,"k":[100,100],"ix":3},"r":{"a":0,"k":0,"ix":6},"o":{"a":0,"k":100,"ix":7},"sk":{"a":0,"k":0,"ix":4},"sa":{"a":0,"k":0,"ix":5},"nm":"Transform"}],"nm":"Group 2","np":2,"cix":2,"bm":0,"ix":2,"mn":"ADBE Vector Group","hd":false},{"ty":"gr","it":[{"ind":0,"ty":"sh","ix":1,"ks":{"a":0,"k":{"i":[[0,0],[-19.935,-6.955],[21.193,-24.043],[18.293,18.728]],"o":[[0,0],[19.936,6.953],[-21.193,24.045],[-18.294,-18.729]],"v":[[-17.982,-40.254],[30.844,-43.089],[30.056,25.998],[-32.954,7.849]],"c":true},"ix":2},"nm":"Path 1","mn":"ADBE Vector Shape - Group","hd":false},{"ty":"fl","c":{"a":0,"k":[0.419999994016,0.231000010173,0.195999998205,1],"ix":4},"o":{"a":0,"k":100,"ix":5},"r":1,"bm":0,"nm":"Fill 1","mn":"ADBE Vector Graphic - Fill","hd":false},{"ty":"tr","p":{"a":0,"k":[1292.227,632.874],"ix":2},"a":{"a":0,"k":[0,0],"ix":1},"s":{"a":0,"k":[100,100],"ix":3},"r":{"a":0,"k":0,"ix":6},"o":{"a":0,"k":100,"ix":7},"sk":{"a":0,"k":0,"ix":4},"sa":{"a":0,"k":0,"ix":5},"nm":"Transform"}],"nm":"Group 3","np":2,"cix":2,"bm":0,"ix":3,"mn":"ADBE Vector Group","hd":false},{"ty":"gr","it":[{"ind":0,"ty":"sh","ix":1,"ks":{"a":0,"k":{"i":[[-10.306,15.506],[31.933,10.988],[2.232,0.128],[9.25,-1.317],[4.87,-1.455],[5.409,-0.94],[-1.622,-5.108],[2.748,0.482],[-0.109,-1.172],[0.163,-3.328],[6.683,-1.033],[-0.688,-7.463],[-22.25,-8.592],[0,0],[-32.525,10.249]],"o":[[18.693,-28.126],[-2.884,-0.993],[-17.86,-1.028],[-9.25,1.318],[-4.869,1.455],[-5.408,0.942],[1.624,5.108],[-2.747,-0.48],[-7.762,0.005],[-0.162,3.327],[-6.684,1.034],[0.687,7.461],[26.574,10.263],[0,0],[6.838,-2.155]],"v":[[76.668,19.279],[51.001,-58.41],[43.261,-60.154],[4.133,-52.32],[-14.068,-40.612],[-52.127,-47.274],[-54.764,-32.213],[-67.553,-23.859],[-68.616,-14.186],[-79.001,-11.179],[-85.913,-2.845],[-94.673,11.25],[-43.22,48.048],[1.617,42.503],[48.657,50.933]],"c":true},"ix":2},"nm":"Path 1","mn":"ADBE Vector Shape - Group","hd":false},{"ty":"fl","c":{"a":0,"k":[0.948999980852,0.620000023935,0.46699999641,1],"ix":4},"o":{"a":0,"k":100,"ix":5},"r":1,"bm":0,"nm":"Fill 1","mn":"ADBE Vector Graphic - Fill","hd":false},{"ty":"tr","p":{"a":0,"k":[1166.191,563.653],"ix":2},"a":{"a":0,"k":[0,0],"ix":1},"s":{"a":0,"k":[100,100],"ix":3},"r":{"a":0,"k":0,"ix":6},"o":{"a":0,"k":100,"ix":7},"sk":{"a":0,"k":0,"ix":4},"sa":{"a":0,"k":0,"ix":5},"nm":"Transform"}],"nm":"Group 4","np":2,"cix":2,"bm":0,"ix":4,"mn":"ADBE Vector Group","hd":false},{"ty":"gr","it":[{"ind":0,"ty":"sh","ix":1,"ks":{"a":0,"k":{"i":[[12.64,-23.221],[18.78,-5.999],[15.691,5.99],[-38.64,15.1],[0,0],[16.223,19.64]],"o":[[0,0],[-23.242,7.424],[-39.114,-14.931],[68.731,-26.858],[0,0],[-23.701,-28.693]],"v":[[-20.406,-62.169],[-20.406,-33.885],[-67.833,-25.156],[-37.728,70.29],[89.477,11.288],[90.724,-44.645]],"c":true},"ix":2},"nm":"Path 1","mn":"ADBE Vector Shape - Group","hd":false},{"ty":"fl","c":{"a":0,"k":[0.898000021542,0.545000023935,0.404000016755,1],"ix":4},"o":{"a":0,"k":100,"ix":5},"r":1,"bm":0,"nm":"Fill 1","mn":"ADBE Vector Graphic - Fill","hd":false},{"ty":"tr","p":{"a":0,"k":[1111.696,622.954],"ix":2},"a":{"a":0,"k":[0,0],"ix":1},"s":{"a":0,"k":[100,100],"ix":3},"r":{"a":0,"k":0,"ix":6},"o":{"a":0,"k":100,"ix":7},"sk":{"a":0,"k":0,"ix":4},"sa":{"a":0,"k":0,"ix":5},"nm":"Transform"}],"nm":"Group 21","np":2,"cix":2,"bm":0,"ix":5,"mn":"ADBE Vector Group","hd":false},{"ty":"tr","p":{"a":0,"k":[1070.897,693.034],"ix":2},"a":{"a":0,"k":[1070.897,693.034],"ix":1},"s":{"a":0,"k":[100,100],"ix":3},"r":{"a":1,"k":[{"i":{"x":[0.667],"y":[1]},"o":{"x":[0.333],"y":[0]},"t":0,"s":[4]},{"i":{"x":[0.667],"y":[1]},"o":{"x":[0.167],"y":[0]},"t":50,"s":[0]},{"i":{"x":[0.667],"y":[1]},"o":{"x":[0.333],"y":[0]},"t":110,"s":[0]},{"t":160,"s":[4]}],"ix":6},"o":{"a":0,"k":100,"ix":7},"sk":{"a":0,"k":0,"ix":4},"sa":{"a":0,"k":0,"ix":5},"nm":"Transform"}],"nm":"Group 31","np":5,"cix":2,"bm":0,"ix":16,"mn":"ADBE Vector Group","hd":false},{"ty":"gr","it":[{"ind":0,"ty":"sh","ix":1,"ks":{"a":0,"k":{"i":[[-27.782,-8.413],[24.375,16.406],[14.775,16.832],[86.043,32.249],[1.884,0.011],[0,0],[0,0],[0,0],[-36.812,-5.023]],"o":[[131.069,39.691],[-25.013,-16.835],[-16.813,-19.153],[-39.974,-2.285],[0,0],[-0.027,0.019],[4.988,6.981],[30.467,0.226],[46.953,6.391]],"v":[[54.785,58.837],[128.363,-25.888],[72.778,-79.375],[-70.877,-88.103],[-184.059,-94.085],[-184.082,-94.09],[-184.131,-94.076],[-185.854,29.386],[-66.397,35.657]],"c":true},"ix":2},"nm":"Path 1","mn":"ADBE Vector Shape - Group","hd":false},{"ty":"fl","c":{"a":0,"k":[0.898000021542,0.545000023935,0.404000016755,1],"ix":4},"o":{"a":0,"k":100,"ix":5},"r":1,"bm":0,"nm":"Fill 1","mn":"ADBE Vector Graphic - Fill","hd":false},{"ty":"tr","p":{"a":0,"k":[943.524,630.734],"ix":2},"a":{"a":0,"k":[0,0],"ix":1},"s":{"a":0,"k":[100,100],"ix":3},"r":{"a":0,"k":0,"ix":6},"o":{"a":0,"k":100,"ix":7},"sk":{"a":0,"k":0,"ix":4},"sa":{"a":0,"k":0,"ix":5},"nm":"Transform"}],"nm":"Group 20","np":2,"cix":2,"bm":0,"ix":17,"mn":"ADBE Vector Group","hd":false},{"ty":"gr","it":[{"ty":"gr","it":[{"ind":0,"ty":"sh","ix":1,"ks":{"a":0,"k":{"i":[[2.537,15.362],[-3.887,10.336],[-10.283,8.195],[15.407,-8.862],[8.628,-12.787],[10.466,-3.553],[-3.94,-10.075],[-4.162,-9.422]],"o":[[-3.886,-7.501],[4.539,-12.069],[10.207,-8.134],[-15.408,8.863],[-8.628,12.786],[-10.466,3.554],[3.94,10.076],[2.978,6.74]],"v":[[13.676,37.663],[17.963,8.863],[33.251,-35.496],[27.455,-44.163],[1.769,-25.844],[-27.076,-3.081],[-39.518,22.154],[-14.602,46.062]],"c":true},"ix":2},"nm":"Path 1","mn":"ADBE Vector Shape - Group","hd":false},{"ty":"fl","c":{"a":0,"k":[0.936999990426,0.611999990426,0.46699999641,1],"ix":4},"o":{"a":0,"k":100,"ix":5},"r":1,"bm":0,"nm":"Fill 1","mn":"ADBE Vector Graphic - Fill","hd":false},{"ty":"tr","p":{"a":0,"k":[566.032,53.275],"ix":2},"a":{"a":0,"k":[0,0],"ix":1},"s":{"a":0,"k":[100,100],"ix":3},"r":{"a":0,"k":0,"ix":6},"o":{"a":0,"k":100,"ix":7},"sk":{"a":0,"k":0,"ix":4},"sa":{"a":0,"k":0,"ix":5},"nm":"Transform"}],"nm":"Group 22","np":2,"cix":2,"bm":0,"ix":1,"mn":"ADBE Vector Group","hd":false},{"ty":"gr","it":[{"ind":0,"ty":"sh","ix":1,"ks":{"a":0,"k":{"i":[[0,0],[3.844,-136.857],[-8.94,34.924],[37.829,186.751],[25.83,-1.309]],"o":[[0,0],[-3.844,136.857],[8.939,-34.924],[0,0],[-25.83,1.309]],"v":[[-28.59,-174.351],[-71.939,54.378],[66.844,121.435],[36.384,-166.883],[4.827,-189.927]],"c":true},"ix":2},"nm":"Path 1","mn":"ADBE Vector Shape - Group","hd":false},{"ty":"fl","c":{"a":0,"k":[0.195999998205,0.195999998205,0.298000021542,1],"ix":4},"o":{"a":0,"k":100,"ix":5},"r":1,"bm":0,"nm":"Fill 1","mn":"ADBE Vector Graphic - Fill","hd":false},{"ty":"tr","p":{"a":0,"k":[578.144,518.19],"ix":2},"a":{"a":0,"k":[0,0],"ix":1},"s":{"a":0,"k":[100,100],"ix":3},"r":{"a":0,"k":0,"ix":6},"o":{"a":0,"k":100,"ix":7},"sk":{"a":0,"k":0,"ix":4},"sa":{"a":0,"k":0,"ix":5},"nm":"Transform"}],"nm":"Group 23","np":2,"cix":2,"bm":0,"ix":2,"mn":"ADBE Vector Group","hd":false},{"ty":"gr","it":[{"ind":0,"ty":"sh","ix":1,"ks":{"a":0,"k":{"i":[[-20.573,-11.056],[-3.556,-22.665],[11.217,14.06],[-10.378,56.091],[-1.689,18.35]],"o":[[8.487,58.995],[6.471,41.333],[-11.212,-14.019],[2.749,-14.978],[10.267,-1.918]],"v":[[18.142,-86.962],[39.861,57.132],[-22.969,59.324],[-35.954,-45.187],[-29.377,-96.548]],"c":true},"ix":2},"nm":"Path 1","mn":"ADBE Vector Shape - Group","hd":false},{"ty":"fl","c":{"a":0,"k":[0.195999998205,0.195999998205,0.298000021542,1],"ix":4},"o":{"a":0,"k":100,"ix":5},"r":1,"bm":0,"nm":"Fill 1","mn":"ADBE Vector Graphic - Fill","hd":false},{"ty":"tr","p":{"a":0,"k":[575.289,298.229],"ix":2},"a":{"a":0,"k":[0,0],"ix":1},"s":{"a":0,"k":[100,100],"ix":3},"r":{"a":0,"k":0,"ix":6},"o":{"a":0,"k":100,"ix":7},"sk":{"a":0,"k":0,"ix":4},"sa":{"a":0,"k":0,"ix":5},"nm":"Transform"}],"nm":"Group 24","np":2,"cix":2,"bm":0,"ix":3,"mn":"ADBE Vector Group","hd":false},{"ty":"gr","it":[{"ind":0,"ty":"sh","ix":1,"ks":{"a":0,"k":{"i":[[1.497,-43.013],[5.195,-52.482],[8.328,57.539],[-0.488,20.177]],"o":[[0,0],[-1.559,15.756],[-7.308,-50.484],[0.524,-21.694]],"v":[[-21.278,-66.182],[-27.516,44.723],[20.747,51.656],[7.82,-67.805]],"c":true},"ix":2},"nm":"Path 1","mn":"ADBE Vector Shape - Group","hd":false},{"ty":"fl","c":{"a":0,"k":[0.936999990426,0.611999990426,0.46699999641,1],"ix":4},"o":{"a":0,"k":100,"ix":5},"r":1,"bm":0,"nm":"Fill 1","mn":"ADBE Vector Graphic - Fill","hd":false},{"ty":"tr","p":{"a":0,"k":[572.722,164.41],"ix":2},"a":{"a":0,"k":[0,0],"ix":1},"s":{"a":0,"k":[100,100],"ix":3},"r":{"a":0,"k":0,"ix":6},"o":{"a":0,"k":100,"ix":7},"sk":{"a":0,"k":0,"ix":4},"sa":{"a":0,"k":0,"ix":5},"nm":"Transform"}],"nm":"Group 25","np":2,"cix":2,"bm":0,"ix":4,"mn":"ADBE Vector Group","hd":false},{"ty":"gr","it":[{"ind":0,"ty":"sh","ix":1,"ks":{"a":0,"k":{"i":[[-5.335,14.831],[-4.068,10.267],[-10.425,8.013],[15.561,-8.591],[8.851,-12.633],[10.527,-3.37],[-3.763,-10.144],[-3.996,-9.493]],"o":[[-1.667,-8.556],[4.75,-11.988],[10.349,-7.955],[-15.561,8.591],[-8.851,12.633],[-10.527,3.369],[3.762,10.143],[2.859,6.792]],"v":[[12.031,37.488],[17.528,9.122],[33.591,-34.961],[27.949,-43.728],[1.945,-25.863],[-27.294,-3.609],[-40.177,21.404],[-17.232,44.172]],"c":true},"ix":2},"nm":"Path 1","mn":"ADBE Vector Shape - Group","hd":false},{"ty":"fl","c":{"a":0,"k":[0.898000021542,0.545000023935,0.404000016755,1],"ix":4},"o":{"a":0,"k":100,"ix":5},"r":1,"bm":0,"nm":"Fill 1","mn":"ADBE Vector Graphic - Fill","hd":false},{"ty":"tr","p":{"a":0,"k":[578.549,56.737],"ix":2},"a":{"a":0,"k":[0,0],"ix":1},"s":{"a":0,"k":[100,100],"ix":3},"r":{"a":0,"k":0,"ix":6},"o":{"a":0,"k":100,"ix":7},"sk":{"a":0,"k":0,"ix":4},"sa":{"a":0,"k":0,"ix":5},"nm":"Transform"}],"nm":"Group 26","np":2,"cix":2,"bm":0,"ix":5,"mn":"ADBE Vector Group","hd":false},{"ty":"gr","it":[{"ind":0,"ty":"sh","ix":1,"ks":{"a":0,"k":{"i":[[0,0],[6.246,-136.768],[-9.551,34.762],[34.545,187.387],[25.849,-0.856]],"o":[[0,0],[-6.246,136.768],[9.552,-34.761],[0,0],[-25.849,0.855]],"v":[[-23.088,-174.429],[-70.445,53.504],[67.139,122.987],[41.745,-165.822],[10.597,-189.416]],"c":true},"ix":2},"nm":"Path 1","mn":"ADBE Vector Shape - Group","hd":false},{"ty":"fl","c":{"a":0,"k":[0.128999986836,0.097999999102,0.19199999641,1],"ix":4},"o":{"a":0,"k":100,"ix":5},"r":1,"bm":0,"nm":"Fill 1","mn":"ADBE Vector Graphic - Fill","hd":false},{"ty":"tr","p":{"a":0,"k":[578.747,514.629],"ix":2},"a":{"a":0,"k":[0,0],"ix":1},"s":{"a":0,"k":[100,100],"ix":3},"r":{"a":0,"k":0,"ix":6},"o":{"a":0,"k":100,"ix":7},"sk":{"a":0,"k":0,"ix":4},"sa":{"a":0,"k":0,"ix":5},"nm":"Transform"}],"nm":"Group 27","np":2,"cix":2,"bm":0,"ix":6,"mn":"ADBE Vector Group","hd":false},{"ty":"gr","it":[{"ind":0,"ty":"sh","ix":1,"ks":{"a":0,"k":{"i":[[-20.376,-11.415],[-3.157,-22.724],[10.969,14.254],[-11.361,55.9],[-2.012,18.317]],"o":[[7.45,59.135],[5.745,41.44],[-10.965,-14.214],[3.011,-14.927],[10.298,-1.738]],"v":[[19.954,-87.007],[39.812,57.584],[-23.047,58.674],[-34.196,-46.05],[-26.718,-97.286]],"c":true},"ix":2},"nm":"Path 1","mn":"ADBE Vector Shape - Group","hd":false},{"ty":"fl","c":{"a":0,"k":[0.128999986836,0.097999999102,0.19199999641,1],"ix":4},"o":{"a":0,"k":100,"ix":5},"r":1,"bm":0,"nm":"Fill 1","mn":"ADBE Vector Graphic - Fill","hd":false},{"ty":"tr","p":{"a":0,"k":[581.232,295.286],"ix":2},"a":{"a":0,"k":[0,0],"ix":1},"s":{"a":0,"k":[100,100],"ix":3},"r":{"a":0,"k":0,"ix":6},"o":{"a":0,"k":100,"ix":7},"sk":{"a":0,"k":0,"ix":4},"sa":{"a":0,"k":0,"ix":5},"nm":"Transform"}],"nm":"Group 28","np":2,"cix":2,"bm":0,"ix":7,"mn":"ADBE Vector Group","hd":false},{"ty":"gr","it":[{"ind":0,"ty":"sh","ix":1,"ks":{"a":0,"k":{"i":[[2.251,-42.98],[6.115,-52.383],[7.317,57.676],[-0.842,20.165]],"o":[[0,0],[-1.836,15.726],[-6.42,-50.605],[0.905,-21.681]],"v":[[-18.624,-66.627],[-26.807,44.152],[21.326,51.931],[10.498,-67.739]],"c":true},"ix":2},"nm":"Path 1","mn":"ADBE Vector Shape - Group","hd":false},{"ty":"fl","c":{"a":0,"k":[0.898000021542,0.545000023935,0.404000016755,1],"ix":4},"o":{"a":0,"k":100,"ix":5},"r":1,"bm":0,"nm":"Fill 1","mn":"ADBE Vector Graphic - Fill","hd":false},{"ty":"tr","p":{"a":0,"k":[580.484,161.285],"ix":2},"a":{"a":0,"k":[0,0],"ix":1},"s":{"a":0,"k":[100,100],"ix":3},"r":{"a":0,"k":0,"ix":6},"o":{"a":0,"k":100,"ix":7},"sk":{"a":0,"k":0,"ix":4},"sa":{"a":0,"k":0,"ix":5},"nm":"Transform"}],"nm":"Group 29","np":2,"cix":2,"bm":0,"ix":8,"mn":"ADBE Vector Group","hd":false},{"ty":"tr","p":{"a":1,"k":[{"i":{"x":0.667,"y":1},"o":{"x":0.333,"y":0},"t":0,"s":[573.175,615.816],"to":[0,-1.667],"ti":[0,1.667]},{"i":{"x":0.667,"y":0.667},"o":{"x":0.167,"y":0.167},"t":50,"s":[573.175,605.816],"to":[0,0],"ti":[0,0]},{"i":{"x":0.667,"y":1},"o":{"x":0.333,"y":0},"t":110,"s":[573.175,605.816],"to":[0,1.667],"ti":[0,-1.667]},{"t":160,"s":[573.175,615.816]}],"ix":2},"a":{"a":0,"k":[573.175,605.816],"ix":1},"s":{"a":0,"k":[100,100],"ix":3},"r":{"a":1,"k":[{"i":{"x":[0.667],"y":[1]},"o":{"x":[0.333],"y":[0]},"t":0,"s":[-91]},{"i":{"x":[0.667],"y":[1]},"o":{"x":[0.167],"y":[0]},"t":50,"s":[0]},{"i":{"x":[0.667],"y":[1]},"o":{"x":[0.333],"y":[0]},"t":110,"s":[0]},{"t":160,"s":[-91]}],"ix":6},"o":{"a":0,"k":100,"ix":7},"sk":{"a":0,"k":0,"ix":4},"sa":{"a":0,"k":0,"ix":5},"nm":"Transform"}],"nm":"Group 32","np":8,"cix":2,"bm":0,"ix":18,"mn":"ADBE Vector Group","hd":false},{"ty":"gr","it":[{"ind":0,"ty":"sh","ix":1,"ks":{"a":0,"k":{"i":[[0,-26.173],[380.892,0],[0,26.172],[-380.891,0]],"o":[[0,26.172],[-380.891,0],[0,-26.173],[380.892,0]],"v":[[689.664,0],[0,47.39],[-689.664,0],[0,-47.39]],"c":true},"ix":2},"nm":"Path 1","mn":"ADBE Vector Shape - Group","hd":false},{"ty":"fl","c":{"a":0,"k":[0.902000038297,0.905999995213,0.910000011968,1],"ix":4},"o":{"a":0,"k":100,"ix":5},"r":1,"bm":0,"nm":"Fill 1","mn":"ADBE Vector Graphic - Fill","hd":false},{"ty":"tr","p":{"a":0,"k":[663.914,676.444],"ix":2},"a":{"a":0,"k":[0,0],"ix":1},"s":{"a":0,"k":[103.514,100],"ix":3},"r":{"a":0,"k":0,"ix":6},"o":{"a":0,"k":100,"ix":7},"sk":{"a":0,"k":0,"ix":4},"sa":{"a":0,"k":0,"ix":5},"nm":"Transform"}],"nm":"Group 30","np":2,"cix":2,"bm":0,"ix":19,"mn":"ADBE Vector Group","hd":false}],"ip":0,"op":180,"st":0,"bm":0}],"markers":[]}